CHANGES.txt
LICENSE.txt
MANIFEST.in
README.rst
distribute_setup.py
setup.py
cfg/ofarchiver.ini
ofarchiver/__init__.py
ofarchiver.egg-info/PKG-INFO
ofarchiver.egg-info/SOURCES.txt
ofarchiver.egg-info/dependency_links.txt
ofarchiver.egg-info/entry_points.txt
ofarchiver.egg-info/requires.txt
ofarchiver.egg-info/top_level.txt