Metadata-Version: 1.0
Name: ofarchiver
Version: 0.43
Summary: An HTML archive generator for chat rooms on an Openfire instant messaging server.
Home-page: http://github.com/egnyte/ofarchiver
Author: John A. Barbuto
Author-email: jbarbuto@egnyte.com
License: MIT
Keywords: archiving,chat,html,openfire
Platform: POSIX
Classifier: Development Status :: 4 - Beta
Classifier: Intended Audience :: System Administrators
Classifier: License :: OSI Approved :: MIT License
Classifier: Operating System :: POSIX
Classifier: Programming Language :: Python :: 2.6
Classifier: Programming Language :: Python :: 2.7
Classifier: Topic :: Communications :: Chat
Classifier: Topic :: System :: Archiving
